zapcli/__init__.py
zapcli/cli.py
zapcli/exceptions.py
zapcli/helpers.py
zapcli/log.py
zapcli/version.py
zapcli/zap_helper.py
zapcli/commands/__init__.py
zapcli/commands/context.py
zapcli/commands/policies.py
zapcli/commands/scanners.py
zapcli/commands/scripts.py
zapcli/commands/session.py
zap_cli_v2-0.12.2.dist-info/LICENSE
zap_cli_v2-0.12.2.dist-info/METADATA
zap_cli_v2-0.12.2.dist-info/WHEEL
zap_cli_v2-0.12.2.dist-info/entry_points.txt
zap_cli_v2-0.12.2.dist-info/top_level.txt
zap_cli_v2-0.12.2.dist-info/RECORD
