Metadata-Version: 2.1
Name: zap-cli-v2
Version: 0.12.2
Summary: A ZAP CLI tool for targeted tests from the command line.
Home-page: https://github.com/kmcquade/zap-cli-v2
Author: Daniel Grunwell (grunny)
Author-email: mwgrunny@gmail.com
License: MIT
Platform: UNKNOWN
Classifier: Topic :: Security
Classifier: Topic :: Software Development :: Quality Assurance
Classifier: Topic :: Software Development :: Testing
Classifier: Topic :: Software Development :: Libraries :: Python Modules
Classifier: Intended Audience :: Developers
Classifier: Intended Audience :: Information Technology
Requires-Dist: click
Requires-Dist: python-owasp-zap-v2.4
Requires-Dist: requests
Requires-Dist: tabulate
Requires-Dist: termcolor
Requires-Dist: six
Provides-Extra: dev
Requires-Dist: coverage ; extra == 'dev'
Requires-Dist: ddt ; extra == 'dev'
Requires-Dist: mock ; extra == 'dev'
Requires-Dist: pep8 ; extra == 'dev'
Requires-Dist: pylint ; extra == 'dev'
Requires-Dist: pytest ; extra == 'dev'
Requires-Dist: responses ; extra == 'dev'
